llama_index/llms/nebius/__init__.py
llama_index/llms/nebius/base.py
llama_index_llms_nebius-0.2.1.dist-info/METADATA
llama_index_llms_nebius-0.2.1.dist-info/WHEEL
llama_index_llms_nebius-0.2.1.dist-info/licenses/LICENSE
llama_index_llms_nebius-0.2.1.dist-info/RECORD
